{
    "stepKey": "overview",
    "stepStr": "Overview",
    "phases": {
        "temporaryMigration": {
            "stepStr": "Temporary Migration",
            "seqIndex": 100,
            "tasks": {
                "task313": {
                    "stepStr": "Task 313",
                    "seqIndex": 100,
                    "subtasks": {
                        "subtask100": {
                            "seqIndex": 100,
                            "stepStr": "Subtask 100"
                        },
                        "subtask110": {
                            "seqIndex": 120,
                            "stepStr": "Subtask 110"
                        }
                    }
                },
                "task220": {
                    "seqIndex": 150,
                    "stepStr": "Task 220",
                    "subtasks": {}
                },
                "task002": {
                    "seqIndex": 150,
                    "stepStr": "Task 002",
                    "subtasks": {}
                }
            }
        },
        "development": {
            "stepStr": "Development",
            "seqIndex": 150,
            "tasks": {}
        },
        "unitTest": {
            "stepStr": "Unit Test With Client",
            "seqIndex": 200,
            "tasks": {}
        }
    }
}